<?xml version="1.0" encoding="UTF-8"?>
<objects serializationModel="Studio.02.03.00">
	<object class="EncodingSetting" id="{01ef95f2-c073-48f7-8915-948f8209bcc8}">
		<property name="encodingFormat">
			<value>3</value>
		</property>
		<property name="quality">
			<value>37</value>
		</property>
		<relationship name="platform">
			<destination>{1607e139-c9b4-4b3b-b910-b8bb80ddedba}</destination>
		</relationship>
		<relationship name="encodable">
			<destination>{1607e139-c9b4-4b3b-b910-b8bb80ddedba}</destination>
		</relationship>
	</object>
</objects>
